Schengen_Borders_Information_Scraper/__init__.py
Schengen_Borders_Information_Scraper/scraper.py
schengen_borders_information_scraper-0.0.1.dist-info/METADATA
schengen_borders_information_scraper-0.0.1.dist-info/WHEEL
schengen_borders_information_scraper-0.0.1.dist-info/licenses/LICENCE
schengen_borders_information_scraper-0.0.1.dist-info/RECORD
