Metadata-Version: 2.1
Name: Schengen_Borders_Information_Scraper
Version: 0.0.1
Summary: This Python script scrapes information about temporary reintroduction of border control in the Schengen Area from the European Commission's website.
Project-URL: Homepage, https://github.com/Markus-Stuppnig/Schengen-Borders-Information-Scraper
Project-URL: Bug Tracker, https://github.com/Markus-Stuppnig/Schengen-Borders-Information-Scraper/issues
Author-email: Markus Stuppnig <accounts@stuppnig.net>
License-File: LICENCE
Classifier: License :: OSI Approved :: MIT License
Classifier: Operating System :: OS Independent
Classifier: Programming Language :: Python :: 3
Requires-Python: >=3.7
Requires-Dist: beautifulsoup4>=4.12.2
Requires-Dist: requests>=2.31.0
